unicorner_face_detector/__init__.py
unicorner_face_detector/face_detector.py
unicorner_face_detector-0.1.0.dist-info/METADATA
unicorner_face_detector-0.1.0.dist-info/WHEEL
unicorner_face_detector-0.1.0.dist-info/top_level.txt
unicorner_face_detector-0.1.0.dist-info/RECORD
