Metadata-Version: 2.4
Name: unicorner-face-detector
Version: 0.1.0
Summary: UNICORNER Coffee’s simple FaceDetector module (YuNet wrapper)
Author-email: Ruslan Kovalev <kovalyovruslan@gmail.com>
Requires-Python: >=3.7
Requires-Dist: opencv-python>=4.5
